README.rst
setup.py
bees/__init__.py
bees/hsearch.py
bees.egg-info/PKG-INFO
bees.egg-info/SOURCES.txt
bees.egg-info/dependency_links.txt
bees.egg-info/not-zip-safe
bees.egg-info/top_level.txt