Metadata-Version: 1.1
Name: bees
Version: 0.1
Summary: Python package example
Home-page: https://github.com/aarontuor/bees
Author: Aaron Tuor
Author-email: tuora@students.wwu.edu
License: none
Keywords: Package Distribution
Platform: UNKNOWN
Classifier: Programming Language :: Python
